cloud_cost_optimizer/__init__.py
cloud_cost_optimizer/cli.py
cloud_cost_optimizer/config.py
cloud_cost_optimizer/core.py
cloud_cost_optimizer/optimizers/__init__.py
cloud_cost_optimizer/optimizers/base.py
cloud_cost_optimizer/optimizers/ebs.py
cloud_cost_optimizer/optimizers/ec2.py
cloud_cost_optimizer/optimizers/elastic_ip.py
cloud_cost_optimizer/optimizers/elb.py
cloud_cost_optimizer/optimizers/public_ip.py
cloud_cost_optimizer/pricing/__init__.py
cloud_cost_optimizer/pricing/models.py
cloud_cost_optimizer/utils/__init__.py
cloud_cost_optimizer/utils/console.py
cloud_cost_optimizer/utils/privacy.py
pyarmor_runtime_000000/__init__.py
pyarmor_runtime_000000/darwin_universal/pyarmor_runtime.so
pyarmor_runtime_000000/linux_aarch64/pyarmor_runtime.so
pyarmor_runtime_000000/linux_armv7/pyarmor_runtime.so
pyarmor_runtime_000000/linux_x86/pyarmor_runtime.so
pyarmor_runtime_000000/linux_x86_64/pyarmor_runtime.so
pyarmor_runtime_000000/windows_x86/pyarmor_runtime.pyd
pyarmor_runtime_000000/windows_x86_64/pyarmor_runtime.pyd
cloudcost-1.0.0.dist-info/LICENSE
cloudcost-1.0.0.dist-info/METADATA
cloudcost-1.0.0.dist-info/WHEEL
cloudcost-1.0.0.dist-info/entry_points.txt
cloudcost-1.0.0.dist-info/top_level.txt
cloudcost-1.0.0.dist-info/RECORD
