Metadata-Version: 2.1
Name: cloudcost
Version: 1.0.0
Summary: Cloud Cost Optimization Tool
Home-page: UNKNOWN
Author: Kaushal
Author-email: kaushal@auron.cloud
License: Proprietary
Project-URL: Home page, https://auron.cloud
Project-URL: Bug Reports, https://github.com/AuronCloud/cloudcost/issues
Project-URL: Source, https://github.com/AuronCloud/cloudcost/
Project-URL: Documentation, https://github.com/AuronCloud/cloudcost/blob/main/README.md
Project-URL: Donate, https://github.com/sponsors/kaushal540
Keywords: aws,cost,optimization,cloud
Platform: UNKNOWN
Classifier: Development Status :: 3 - Alpha
Classifier: Intended Audience :: System Administrators
Classifier: License :: Other/Proprietary License
Classifier: Operating System :: OS Independent
Classifier: Programming Language :: Python :: 3
Classifier: Programming Language :: Python :: 3.9
Classifier: Programming Language :: Python :: 3.10
Classifier: Programming Language :: Python :: 3.11
Classifier: Programming Language :: Python :: 3.12
Requires-Python: >=3.9
License-File: LICENSE
Requires-Dist: boto3>=1.20.0
Requires-Dist: colorama>=0.4.4
Requires-Dist: tabulate>=0.8.9
Requires-Dist: botocore~=1.37.13
Requires-Dist: setuptools~=70.0.0
Requires-Dist: requests~=2.32.3
Requires-Dist: sentry-sdk~=2.24.0
